{
    "NAME1": "K E N J I ",
    "NAME2": "C A S T R O", 
    "NAME3": "I L A O",
    "Course": "COMPUTER ENGINEERING STUDENT", 

    "Personal Profile1": "I am a Engineering student that want",
    "Personal Profile2": " a bright future ",


    "Mobile": "09566516363",
    "Gmail": "wendyroselane@gmail.com",
    "Address1": "Sampaguita st.brgy dela paz",
    "Address2": "Antipolo City, Rizal 1870",

    "Skills and Abilities1": " -Time management",
    "Skills and Abilities2": " -Problem-solving",
    "Skills and Abilities3A": "-Management skills",
    "Skills and Abilities3B": "-Communication",
    "Skills and Abilities4": " -Fast learner",
    "Skills and Abilities5": " -Active listening",
    "Skills and Abilities6": " -Hard working",
    "Skills and Abilities7": " -Motivated",

    "Facebook": "ijnek",
    "Instagram": "ijnekoali",
    "Github": "kenjiilao",

    "School SHS": "Our Lady of Fatima University    ",
    "Strand SHS1": "Science, Technology, Engineering and",
    "Strand SHS2": "Mathematics (STEM)",
    "SHS Description1": "Graduated Class of 2021",
    "SHS Description2": "-With High Honor",
    "SHS Achievement1": "-Champion in Olymphysics",

    "School JHS1": "Sta Cruz Elementary School ",
    "JHS Description1": "Graduated Class of 2019",
    "JHS Description2": "-With Honor "
}
